[{"id":1,"kode_provinsi":32,"nama_provinsi":"JAWA BARAT","kode_kabupaten_kota":3201,"nama_kabupaten_kota":"KABUPATEN BOGOR","jumlah_masjid":2360,"satuan":"UNIT","tahun":2021},{"id":2,"kode_provinsi":32,"nama_provinsi":"JAWA BARAT","kode_kabupaten_kota":3202,"nama_kabupaten_kota":"KABUPATEN SUKABUMI","jumlah_masjid":5226,"satuan":"UNIT","tahun":2021},{"id":3,"kode_provinsi":32,"nama_provinsi":"JAWA BARAT","kode_kabupaten_kota":3203,"nama_kabupaten_kota":"KABUPATEN CIANJUR","jumlah_masjid":5533,"satuan":"UNIT","tahun":2021},{"id":4,"kode_provinsi":32,"nama_provinsi":"JAWA BARAT","kode_kabupaten_kota":3204,"nama_kabupaten_kota":"KABUPATEN BANDUNG","jumlah_masjid":5325,"satuan":"UNIT","tahun":2021},{"id":5,"kode_provinsi":32,"nama_provinsi":"JAWA BARAT","kode_kabupaten_kota":3205,"nama_kabupaten_kota":"KABUPATEN GARUT","jumlah_masjid":3262,"satuan":"UNIT","tahun":2021},{"id":6,"kode_provinsi":32,"nama_provinsi":"JAWA BARAT","kode_kabupaten_kota":3206,"nama_kabupaten_kota":"KABUPATEN TASIKMALAYA","jumlah_masjid":4059,"satuan":"UNIT","tahun":2021},{"id":7,"kode_provinsi":32,"nama_provinsi":"JAWA BARAT","kode_kabupaten_kota":3207,"nama_kabupaten_kota":"KABUPATEN CIAMIS","jumlah_masjid":2453,"satuan":"UNIT","tahun":2021},{"id":8,"kode_provinsi":32,"nama_provinsi":"JAWA BARAT","kode_kabupaten_kota":3208,"nama_kabupaten_kota":"KABUPATEN KUNINGAN","jumlah_masjid":806,"satuan":"UNIT","tahun":2021},{"id":9,"kode_provinsi":32,"nama_provinsi":"JAWA BARAT","kode_kabupaten_kota":3209,"nama_kabupaten_kota":"KABUPATEN CIREBON","jumlah_masjid":822,"satuan":"UNIT","tahun":2021},{"id":10,"kode_provinsi":32,"nama_provinsi":"JAWA BARAT","kode_kabupaten_kota":3210,"nama_kabupaten_kota":"KABUPATEN MAJALENGKA","jumlah_masjid":1014,"satuan":"UNIT","tahun":2021},{"id":11,"kode_provinsi":32,"nama_provinsi":"JAWA BARAT","kode_kabupaten_kota":3211,"nama_kabupaten_kota":"KABUPATEN SUMEDANG","jumlah_masjid":2299,"satuan":"UNIT","tahun":2021},{"id":12,"kode_provinsi":32,"nama_provinsi":"JAWA BARAT","kode_kabupaten_kota":3212,"nama_kabupaten_kota":"KABUPATEN INDRAMAYU","jumlah_masjid":805,"satuan":"UNIT","tahun":2021},{"id":13,"kode_provinsi":32,"nama_provinsi":"JAWA BARAT","kode_kabupaten_kota":3213,"nama_kabupaten_kota":"KABUPATEN SUBANG","jumlah_masjid":1665,"satuan":"UNIT","tahun":2021},{"id":14,"kode_provinsi":32,"nama_provinsi":"JAWA BARAT","kode_kabupaten_kota":3214,"nama_kabupaten_kota":"KABUPATEN PURWAKARTA","jumlah_masjid":975,"satuan":"UNIT","tahun":2021},{"id":15,"kode_provinsi":32,"nama_provinsi":"JAWA BARAT","kode_kabupaten_kota":3215,"nama_kabupaten_kota":"KABUPATEN KARAWANG","jumlah_masjid":1628,"satuan":"UNIT","tahun":2021},{"id":16,"kode_provinsi":32,"nama_provinsi":"JAWA BARAT","kode_kabupaten_kota":3216,"nama_kabupaten_kota":"KABUPATEN BEKASI","jumlah_masjid":661,"satuan":"UNIT","tahun":2021},{"id":17,"kode_provinsi":32,"nama_provinsi":"JAWA BARAT","kode_kabupaten_kota":3217,"nama_kabupaten_kota":"KABUPATEN BANDUNG BARAT","jumlah_masjid":3261,"satuan":"UNIT","tahun":2021},{"id":18,"kode_provinsi":32,"nama_provinsi":"JAWA BARAT","kode_kabupaten_kota":3218,"nama_kabupaten_kota":"KABUPATEN PANGANDARAN","jumlah_masjid":845,"satuan":"UNIT","tahun":2021},{"id":19,"kode_provinsi":32,"nama_provinsi":"JAWA BARAT","kode_kabupaten_kota":3271,"nama_kabupaten_kota":"KOTA BOGOR","jumlah_masjid":785,"satuan":"UNIT","tahun":2021},{"id":20,"kode_provinsi":32,"nama_provinsi":"JAWA BARAT","kode_kabupaten_kota":3272,"nama_kabupaten_kota":"KOTA SUKABUMI","jumlah_masjid":354,"satuan":"UNIT","tahun":2021},{"id":21,"kode_provinsi":32,"nama_provinsi":"JAWA BARAT","kode_kabupaten_kota":3273,"nama_kabupaten_kota":"KOTA BANDUNG","jumlah_masjid":2243,"satuan":"UNIT","tahun":2021},{"id":22,"kode_provinsi":32,"nama_provinsi":"JAWA BARAT","kode_kabupaten_kota":3274,"nama_kabupaten_kota":"KOTA CIREBON","jumlah_masjid":301,"satuan":"UNIT","tahun":2021},{"id":23,"kode_provinsi":32,"nama_provinsi":"JAWA BARAT","kode_kabupaten_kota":3275,"nama_kabupaten_kota":"KOTA BEKASI","jumlah_masjid":554,"satuan":"UNIT","tahun":2021},{"id":24,"kode_provinsi":32,"nama_provinsi":"JAWA BARAT","kode_kabupaten_kota":3276,"nama_kabupaten_kota":"KOTA DEPOK","jumlah_masjid":446,"satuan":"UNIT","tahun":2021},{"id":25,"kode_provinsi":32,"nama_provinsi":"JAWA BARAT","kode_kabupaten_kota":3277,"nama_kabupaten_kota":"KOTA CIMAHI","jumlah_masjid":420,"satuan":"UNIT","tahun":2021},{"id":26,"kode_provinsi":32,"nama_provinsi":"JAWA BARAT","kode_kabupaten_kota":3278,"nama_kabupaten_kota":"KOTA TASIKMALAYA","jumlah_masjid":1013,"satuan":"UNIT","tahun":2021},{"id":27,"kode_provinsi":32,"nama_provinsi":"JAWA BARAT","kode_kabupaten_kota":3279,"nama_kabupaten_kota":"KOTA BANJAR","jumlah_masjid":320,"satuan":"UNIT","tahun":2021}]